oxansi/__init__.py
oxansi/main.py
oxansi-0.0.3.dist-info/METADATA
oxansi-0.0.3.dist-info/WHEEL
oxansi-0.0.3.dist-info/top_level.txt
oxansi-0.0.3.dist-info/RECORD
